sync_dataclasses/SyncDataClass.py
sync_dataclasses/__init__.py
sync_dataclasses-0.1.0.dist-info/licenses/LICENSE
sync_dataclasses-0.1.0.dist-info/METADATA
sync_dataclasses-0.1.0.dist-info/WHEEL
sync_dataclasses-0.1.0.dist-info/top_level.txt
sync_dataclasses-0.1.0.dist-info/RECORD
